{
    "ethereum": {
        "default": "main",
        "nodeUrlDefault": {
            "private": "http://localhost:8545",
            "rinkeby": "https://rinkeby.infura.io/v3/aeae830838614da186df7984467a2d2d",
            "main": "https://mainnet.infura.io/v3/aeae830838614da186df7984467a2d2d"
        },
        "defaultNumberOfConfirmation": 1,
        "gasPriceDefault": "4",
        "gasPriceDefaultUnit": "gwei",
        "gasPriceMinimumCriticalInWei": 100000000
    },
    "bitcoin": {
        "default": 0
    },
    "ipfs": {
        "nodeUrlDefault": {
            "private": {
                "host": "localhost",
                "port": "5001",
                "protocol": "http"
            },
            "public": {
                "host": "ipfs.infura.io",
                "port": "5001",
                "protocol": "https"
            }
        },
        "timeout": 10000
    }
}
